u64cmd/__init__.py
u64cmd/__main__.py
u64cmd/cli.py
u64cmd/socket.py
u64cmd/util.py
u64cmd-0.9.1.dist-info/METADATA
u64cmd-0.9.1.dist-info/WHEEL
u64cmd-0.9.1.dist-info/entry_points.txt
u64cmd-0.9.1.dist-info/top_level.txt
u64cmd-0.9.1.dist-info/RECORD
