Metadata-Version: 2.1
Name: u64cmd
Version: 0.9.1
Summary: A command line tool to remote control your Ultimate 64 or Ultimate II+ device.
Author-email: Christian Vogelgsang <chris@vogelgsang.org>
License: BSD
Keywords: C64,Ultimate 64,Ultimate II+,Ultimate 1541
Classifier: Development Status :: 4 - Beta
Classifier: Intended Audience :: Developers
Classifier: Programming Language :: Python
Requires-Python: >=3.7
Requires-Dist: click
